{
  "addresses": [
    {
      "hnrlbls": [
        "1"
      ], 
      "housenumber": "1", 
      "lat": 50.463810517075, 
      "lon": 4.101388950557, 
      "municipality": "La Louvi\u00e8re", 
      "pcode": "7110", 
      "source": "7717180", 
      "street": "Rue Charles Bernier"
    }, 
    {
      "hnrlbls": [
        "10"
      ], 
      "housenumber": "10", 
      "lat": 50.463264173071, 
      "lon": 4.101560715288, 
      "municipality": "La Louvi\u00e8re", 
      "pcode": "7110", 
      "source": "7717180", 
      "street": "Rue Charles Bernier"
    }, 
    {
      "hnrlbls": [
        "11"
      ], 
      "housenumber": "11", 
      "lat": 50.464010339376, 
      "lon": 4.101888920036, 
      "municipality": "La Louvi\u00e8re", 
      "pcode": "7110", 
      "source": "7717180", 
      "street": "Rue Charles Bernier"
    }, 
    {
      "hnrlbls": [
        "12"
      ], 
      "housenumber": "12", 
      "lat": 50.463245975702, 
      "lon": 4.101642719225, 
      "municipality": "La Louvi\u00e8re", 
      "pcode": "7110", 
      "source": "7717180", 
      "street": "Rue Charles Bernier"
    }, 
    {
      "hnrlbls": [
        "13"
      ], 
      "housenumber": "13", 
      "lat": 50.464105991198, 
      "lon": 4.102039907084, 
      "municipality": "La Louvi\u00e8re", 
      "pcode": "7110", 
      "source": "7717180", 
      "street": "Rue Charles Bernier"
    }, 
    {
      "hnrlbls": [
        "14"
      ], 
      "housenumber": "14", 
      "lat": 50.463227831765, 
      "lon": 4.101724525615, 
      "municipality": "La Louvi\u00e8re", 
      "pcode": "7110", 
      "source": "7717180", 
      "street": "Rue Charles Bernier"
    }, 
    {
      "hnrlbls": [
        "15"
      ], 
      "housenumber": "15", 
      "lat": 50.464136737138, 
      "lon": 4.102133849182, 
      "municipality": "La Louvi\u00e8re", 
      "pcode": "7110", 
      "source": "7717180", 
      "street": "Rue Charles Bernier"
    }, 
    {
      "hnrlbls": [
        "16"
      ], 
      "housenumber": "16", 
      "lat": 50.463209643497, 
      "lon": 4.101806627966, 
      "municipality": "La Louvi\u00e8re", 
      "pcode": "7110", 
      "source": "7717180", 
      "street": "Rue Charles Bernier"
    }, 
    {
      "hnrlbls": [
        "17"
      ], 
      "housenumber": "17", 
      "lat": 50.464084745926, 
      "lon": 4.10219670555, 
      "municipality": "La Louvi\u00e8re", 
      "pcode": "7110", 
      "source": "7717180", 
      "street": "Rue Charles Bernier"
    }, 
    {
      "hnrlbls": [
        "18"
      ], 
      "housenumber": "18", 
      "lat": 50.463335237832, 
      "lon": 4.101959627288, 
      "municipality": "La Louvi\u00e8re", 
      "pcode": "7110", 
      "source": "7717180", 
      "street": "Rue Charles Bernier"
    }, 
    {
      "hnrlbls": [
        "19"
      ], 
      "housenumber": "19", 
      "lat": 50.464078210899, 
      "lon": 4.102287603183, 
      "municipality": "La Louvi\u00e8re", 
      "pcode": "7110", 
      "source": "7717180", 
      "street": "Rue Charles Bernier"
    }, 
    {
      "hnrlbls": [
        "2"
      ], 
      "housenumber": "2", 
      "lat": 50.463639086274, 
      "lon": 4.100647371912, 
      "municipality": "La Louvi\u00e8re", 
      "pcode": "7110", 
      "source": "7717180", 
      "street": "Rue Charles Bernier"
    }, 
    {
      "hnrlbls": [
        "20"
      ], 
      "housenumber": "20", 
      "lat": 50.463390751659, 
      "lon": 4.101990442529, 
      "municipality": "La Louvi\u00e8re", 
      "pcode": "7110", 
      "source": "7717180", 
      "street": "Rue Charles Bernier"
    }, 
    {
      "hnrlbls": [
        "21"
      ], 
      "housenumber": "21", 
      "lat": 50.463919547078, 
      "lon": 4.102266802436, 
      "municipality": "La Louvi\u00e8re", 
      "pcode": "7110", 
      "source": "7717180", 
      "street": "Rue Charles Bernier"
    }, 
    {
      "hnrlbls": [
        "22"
      ], 
      "housenumber": "22", 
      "lat": 50.463494055928, 
      "lon": 4.102047848939, 
      "municipality": "La Louvi\u00e8re", 
      "pcode": "7110", 
      "source": "7717180", 
      "street": "Rue Charles Bernier"
    }, 
    {
      "hnrlbls": [
        "23"
      ], 
      "housenumber": "23", 
      "lat": 50.463901081051, 
      "lon": 4.102349484806, 
      "municipality": "La Louvi\u00e8re", 
      "pcode": "7110", 
      "source": "7717180", 
      "street": "Rue Charles Bernier"
    }, 
    {
      "hnrlbls": [
        "24"
      ], 
      "housenumber": "24", 
      "lat": 50.463548776434, 
      "lon": 4.102077725169, 
      "municipality": "La Louvi\u00e8re", 
      "pcode": "7110", 
      "source": "7717180", 
      "street": "Rue Charles Bernier"
    }, 
    {
      "hnrlbls": [
        "25"
      ], 
      "housenumber": "25", 
      "lat": 50.463882641937, 
      "lon": 4.102432166961, 
      "municipality": "La Louvi\u00e8re", 
      "pcode": "7110", 
      "source": "7717180", 
      "street": "Rue Charles Bernier"
    }, 
    {
      "hnrlbls": [
        "26"
      ], 
      "housenumber": "26", 
      "lat": 50.463552214915, 
      "lon": 4.102319496761, 
      "municipality": "La Louvi\u00e8re", 
      "pcode": "7110", 
      "source": "7717180", 
      "street": "Rue Charles Bernier"
    }, 
    {
      "hnrlbls": [
        "27"
      ], 
      "housenumber": "27", 
      "lat": 50.463864211721, 
      "lon": 4.102514834917, 
      "municipality": "La Louvi\u00e8re", 
      "pcode": "7110", 
      "source": "7717180", 
      "street": "Rue Charles Bernier"
    }, 
    {
      "hnrlbls": [
        "28"
      ], 
      "housenumber": "28", 
      "lat": 50.46353289486, 
      "lon": 4.102406155122, 
      "municipality": "La Louvi\u00e8re", 
      "pcode": "7110", 
      "source": "7717180", 
      "street": "Rue Charles Bernier"
    }, 
    {
      "hnrlbls": [
        "29"
      ], 
      "housenumber": "29", 
      "lat": 50.463890764628, 
      "lon": 4.102686195935, 
      "municipality": "La Louvi\u00e8re", 
      "pcode": "7110", 
      "source": "7717180", 
      "street": "Rue Charles Bernier"
    }, 
    {
      "hnrlbls": [
        "3"
      ], 
      "housenumber": "3", 
      "lat": 50.463789161255, 
      "lon": 4.101555974458, 
      "municipality": "La Louvi\u00e8re", 
      "pcode": "7110", 
      "source": "7717180", 
      "street": "Rue Charles Bernier"
    }, 
    {
      "hnrlbls": [
        "30"
      ], 
      "housenumber": "30", 
      "lat": 50.463563981512, 
      "lon": 4.102582531785, 
      "municipality": "La Louvi\u00e8re", 
      "pcode": "7110", 
      "source": "7717180", 
      "street": "Rue Charles Bernier"
    }, 
    {
      "hnrlbls": [
        "31"
      ], 
      "housenumber": "31", 
      "lat": 50.463872346691, 
      "lon": 4.102770384887, 
      "municipality": "La Louvi\u00e8re", 
      "pcode": "7110", 
      "source": "7717180", 
      "street": "Rue Charles Bernier"
    }, 
    {
      "hnrlbls": [
        "32"
      ], 
      "housenumber": "32", 
      "lat": 50.463544885053, 
      "lon": 4.102668766268, 
      "municipality": "La Louvi\u00e8re", 
      "pcode": "7110", 
      "source": "7717180", 
      "street": "Rue Charles Bernier"
    }, 
    {
      "hnrlbls": [
        "33"
      ], 
      "housenumber": "33", 
      "lat": 50.463898230574, 
      "lon": 4.102944214647, 
      "municipality": "La Louvi\u00e8re", 
      "pcode": "7110", 
      "source": "7717180", 
      "street": "Rue Charles Bernier"
    }, 
    {
      "hnrlbls": [
        "34"
      ], 
      "housenumber": "34", 
      "lat": 50.463575733387, 
      "lon": 4.102843313477, 
      "municipality": "La Louvi\u00e8re", 
      "pcode": "7110", 
      "source": "7717180", 
      "street": "Rue Charles Bernier"
    }, 
    {
      "hnrlbls": [
        "35"
      ], 
      "housenumber": "35", 
      "lat": 50.463878994181, 
      "lon": 4.103028337664, 
      "municipality": "La Louvi\u00e8re", 
      "pcode": "7110", 
      "source": "7717180", 
      "street": "Rue Charles Bernier"
    }, 
    {
      "hnrlbls": [
        "36"
      ], 
      "housenumber": "36", 
      "lat": 50.463555853783, 
      "lon": 4.102929200141, 
      "municipality": "La Louvi\u00e8re", 
      "pcode": "7110", 
      "source": "7717180", 
      "street": "Rue Charles Bernier"
    }, 
    {
      "hnrlbls": [
        "37"
      ], 
      "housenumber": "37", 
      "lat": 50.463905510712, 
      "lon": 4.103203797881, 
      "municipality": "La Louvi\u00e8re", 
      "pcode": "7110", 
      "source": "7717180", 
      "street": "Rue Charles Bernier"
    }, 
    {
      "hnrlbls": [
        "38"
      ], 
      "housenumber": "38", 
      "lat": 50.463576214153, 
      "lon": 4.103109510469, 
      "municipality": "La Louvi\u00e8re", 
      "pcode": "7110", 
      "source": "7717180", 
      "street": "Rue Charles Bernier"
    }, 
    {
      "hnrlbls": [
        "39"
      ], 
      "housenumber": "39", 
      "lat": 50.463886794282, 
      "lon": 4.103287354511, 
      "municipality": "La Louvi\u00e8re", 
      "pcode": "7110", 
      "source": "7717180", 
      "street": "Rue Charles Bernier"
    }, 
    {
      "hnrlbls": [
        "4"
      ], 
      "housenumber": "4", 
      "lat": 50.463534733986, 
      "lon": 4.101324093288, 
      "municipality": "La Louvi\u00e8re", 
      "pcode": "7110", 
      "source": "7717180", 
      "street": "Rue Charles Bernier"
    }, 
    {
      "hnrlbls": [
        "40"
      ], 
      "housenumber": "40", 
      "lat": 50.463556494734, 
      "lon": 4.103194762317, 
      "municipality": "La Louvi\u00e8re", 
      "pcode": "7110", 
      "source": "7717180", 
      "street": "Rue Charles Bernier"
    }, 
    {
      "hnrlbls": [
        "41"
      ], 
      "housenumber": "41", 
      "lat": 50.463853173371, 
      "lon": 4.103442713716, 
      "municipality": "La Louvi\u00e8re", 
      "pcode": "7110", 
      "source": "7717180", 
      "street": "Rue Charles Bernier"
    }, 
    {
      "hnrlbls": [
        "42"
      ], 
      "housenumber": "42", 
      "lat": 50.463537816204, 
      "lon": 4.103362121658, 
      "municipality": "La Louvi\u00e8re", 
      "pcode": "7110", 
      "source": "7717180", 
      "street": "Rue Charles Bernier"
    }, 
    {
      "hnrlbls": [
        "43"
      ], 
      "housenumber": "43", 
      "lat": 50.463833990558, 
      "lon": 4.10352683615, 
      "municipality": "La Louvi\u00e8re", 
      "pcode": "7110", 
      "source": "7717180", 
      "street": "Rue Charles Bernier"
    }, 
    {
      "hnrlbls": [
        "44"
      ], 
      "housenumber": "44", 
      "lat": 50.463517737471, 
      "lon": 4.103447586606, 
      "municipality": "La Louvi\u00e8re", 
      "pcode": "7110", 
      "source": "7717180", 
      "street": "Rue Charles Bernier"
    }, 
    {
      "hnrlbls": [
        "45"
      ], 
      "housenumber": "45", 
      "lat": 50.46379984639, 
      "lon": 4.103681535947, 
      "municipality": "La Louvi\u00e8re", 
      "pcode": "7110", 
      "source": "7717180", 
      "street": "Rue Charles Bernier"
    }, 
    {
      "hnrlbls": [
        "46"
      ], 
      "housenumber": "46", 
      "lat": 50.463482179974, 
      "lon": 4.103609335621, 
      "municipality": "La Louvi\u00e8re", 
      "pcode": "7110", 
      "source": "7717180", 
      "street": "Rue Charles Bernier"
    }, 
    {
      "hnrlbls": [
        "47"
      ], 
      "housenumber": "47", 
      "lat": 50.463780700966, 
      "lon": 4.103766362216, 
      "municipality": "La Louvi\u00e8re", 
      "pcode": "7110", 
      "source": "7717180", 
      "street": "Rue Charles Bernier"
    }, 
    {
      "hnrlbls": [
        "48"
      ], 
      "housenumber": "48", 
      "lat": 50.463463062532, 
      "lon": 4.103694583733, 
      "municipality": "La Louvi\u00e8re", 
      "pcode": "7110", 
      "source": "7717180", 
      "street": "Rue Charles Bernier"
    }, 
    {
      "hnrlbls": [
        "49"
      ], 
      "housenumber": "49", 
      "lat": 50.463745295352, 
      "lon": 4.103923927887, 
      "municipality": "La Louvi\u00e8re", 
      "pcode": "7110", 
      "source": "7717180", 
      "street": "Rue Charles Bernier"
    }, 
    {
      "hnrlbls": [
        "5"
      ], 
      "housenumber": "5", 
      "lat": 50.463802286211, 
      "lon": 4.101775410818, 
      "municipality": "La Louvi\u00e8re", 
      "pcode": "7110", 
      "source": "7717180", 
      "street": "Rue Charles Bernier"
    }, 
    {
      "hnrlbls": [
        "50"
      ], 
      "housenumber": "50", 
      "lat": 50.463413868079, 
      "lon": 4.103845211146, 
      "municipality": "La Louvi\u00e8re", 
      "pcode": "7110", 
      "source": "7717180", 
      "street": "Rue Charles Bernier"
    }, 
    {
      "hnrlbls": [
        "51"
      ], 
      "housenumber": "51", 
      "lat": 50.463727091069, 
      "lon": 4.104007579687, 
      "municipality": "La Louvi\u00e8re", 
      "pcode": "7110", 
      "source": "7717180", 
      "street": "Rue Charles Bernier"
    }, 
    {
      "hnrlbls": [
        "52"
      ], 
      "housenumber": "52", 
      "lat": 50.463378460308, 
      "lon": 4.103918718778, 
      "municipality": "La Louvi\u00e8re", 
      "pcode": "7110", 
      "source": "7717180", 
      "street": "Rue Charles Bernier"
    }, 
    {
      "hnrlbls": [
        "53"
      ], 
      "housenumber": "53", 
      "lat": 50.463692869962, 
      "lon": 4.104160349614, 
      "municipality": "La Louvi\u00e8re", 
      "pcode": "7110", 
      "source": "7717180", 
      "street": "Rue Charles Bernier"
    }, 
    {
      "hnrlbls": [
        "55"
      ], 
      "housenumber": "55", 
      "lat": 50.463673820046, 
      "lon": 4.10424383692, 
      "municipality": "La Louvi\u00e8re", 
      "pcode": "7110", 
      "source": "7717180", 
      "street": "Rue Charles Bernier"
    }, 
    {
      "hnrlbls": [
        "6"
      ], 
      "housenumber": "6", 
      "lat": 50.463488122002, 
      "lon": 4.10152144163, 
      "municipality": "La Louvi\u00e8re", 
      "pcode": "7110", 
      "source": "7717180", 
      "street": "Rue Charles Bernier"
    }, 
    {
      "hnrlbls": [
        "7"
      ], 
      "housenumber": "7", 
      "lat": 50.463856296622, 
      "lon": 4.101805319086, 
      "municipality": "La Louvi\u00e8re", 
      "pcode": "7110", 
      "source": "7717180", 
      "street": "Rue Charles Bernier"
    }, 
    {
      "hnrlbls": [
        "8"
      ], 
      "housenumber": "8", 
      "lat": 50.46346868041, 
      "lon": 4.101605805095, 
      "municipality": "La Louvi\u00e8re", 
      "pcode": "7110", 
      "source": "7717180", 
      "street": "Rue Charles Bernier"
    }, 
    {
      "hnrlbls": [
        "9"
      ], 
      "housenumber": "9", 
      "lat": 50.463956842525, 
      "lon": 4.101859487572, 
      "municipality": "La Louvi\u00e8re", 
      "pcode": "7110", 
      "source": "7717180", 
      "street": "Rue Charles Bernier"
    }
  ]
}