{
  "addresses": [
    {
      "hnrlbls": [
        "1"
      ], 
      "housenumber": "1", 
      "lat": 50.480881194986, 
      "lon": 4.119790347654, 
      "municipality": "La Louvi\u00e8re", 
      "pcode": "7110", 
      "source": "7717479", 
      "street": "Rue des Sports"
    }, 
    {
      "hnrlbls": [
        "10"
      ], 
      "housenumber": "10", 
      "lat": 50.481589503925, 
      "lon": 4.120026348671, 
      "municipality": "La Louvi\u00e8re", 
      "pcode": "7110", 
      "source": "7717479", 
      "street": "Rue des Sports"
    }, 
    {
      "hnrlbls": [
        "100"
      ], 
      "housenumber": "100", 
      "lat": 50.483784191464, 
      "lon": 4.119771550647, 
      "municipality": "La Louvi\u00e8re", 
      "pcode": "7110", 
      "source": "7717479", 
      "street": "Rue des Sports"
    }, 
    {
      "hnrlbls": [
        "102"
      ], 
      "housenumber": "102", 
      "lat": 50.483847009819, 
      "lon": 4.119765051111, 
      "municipality": "La Louvi\u00e8re", 
      "pcode": "7110", 
      "source": "7717479", 
      "street": "Rue des Sports"
    }, 
    {
      "hnrlbls": [
        "104"
      ], 
      "housenumber": "104", 
      "lat": 50.483907461454, 
      "lon": 4.11975874996, 
      "municipality": "La Louvi\u00e8re", 
      "pcode": "7110", 
      "source": "7717479", 
      "street": "Rue des Sports"
    }, 
    {
      "hnrlbls": [
        "13"
      ], 
      "housenumber": "13", 
      "lat": 50.48121339437, 
      "lon": 4.11966775796, 
      "municipality": "La Louvi\u00e8re", 
      "pcode": "7110", 
      "source": "7717479", 
      "street": "Rue des Sports"
    }, 
    {
      "hnrlbls": [
        "15"
      ], 
      "housenumber": "15", 
      "lat": 50.48131592856, 
      "lon": 4.119684565041, 
      "municipality": "La Louvi\u00e8re", 
      "pcode": "7110", 
      "source": "7717479", 
      "street": "Rue des Sports"
    }, 
    {
      "hnrlbls": [
        "2"
      ], 
      "housenumber": "2", 
      "lat": 50.48085844902, 
      "lon": 4.12016540961, 
      "municipality": "La Louvi\u00e8re", 
      "pcode": "7110", 
      "source": "7717479", 
      "street": "Rue des Sports"
    }, 
    {
      "hnrlbls": [
        "25"
      ], 
      "housenumber": "25", 
      "lat": 50.481573653402, 
      "lon": 4.119642522009, 
      "municipality": "La Louvi\u00e8re", 
      "pcode": "7110", 
      "source": "7717479", 
      "street": "Rue des Sports"
    }, 
    {
      "hnrlbls": [
        "3"
      ], 
      "housenumber": "3", 
      "lat": 50.480931158266, 
      "lon": 4.119779687564, 
      "municipality": "La Louvi\u00e8re", 
      "pcode": "7110", 
      "source": "7717479", 
      "street": "Rue des Sports"
    }, 
    {
      "hnrlbls": [
        "31"
      ], 
      "housenumber": "31", 
      "lat": 50.481730031696, 
      "lon": 4.119613592423, 
      "municipality": "La Louvi\u00e8re", 
      "pcode": "7110", 
      "source": "7717479", 
      "street": "Rue des Sports"
    }, 
    {
      "hnrlbls": [
        "33"
      ], 
      "housenumber": "33", 
      "lat": 50.481783240562, 
      "lon": 4.119602985384, 
      "municipality": "La Louvi\u00e8re", 
      "pcode": "7110", 
      "source": "7717479", 
      "street": "Rue des Sports"
    }, 
    {
      "hnrlbls": [
        "35"
      ], 
      "housenumber": "35", 
      "lat": 50.481928771778, 
      "lon": 4.119491840431, 
      "municipality": "La Louvi\u00e8re", 
      "pcode": "7110", 
      "source": "7717479", 
      "street": "Rue des Sports"
    }, 
    {
      "hnrlbls": [
        "36"
      ], 
      "housenumber": "36", 
      "lat": 50.481708696474, 
      "lon": 4.120000700766, 
      "municipality": "La Louvi\u00e8re", 
      "pcode": "7110", 
      "source": "7717479", 
      "street": "Rue des Sports"
    }, 
    {
      "hnrlbls": [
        "4"
      ], 
      "housenumber": "4", 
      "lat": 50.481003251534, 
      "lon": 4.120150815741, 
      "municipality": "La Louvi\u00e8re", 
      "pcode": "7110", 
      "source": "7717479", 
      "street": "Rue des Sports"
    }, 
    {
      "hnrlbls": [
        "48"
      ], 
      "housenumber": "48", 
      "lat": 50.481872173254, 
      "lon": 4.120030238476, 
      "municipality": "La Louvi\u00e8re", 
      "pcode": "7110", 
      "source": "7717479", 
      "street": "Rue des Sports"
    }, 
    {
      "hnrlbls": [
        "5"
      ], 
      "housenumber": "5", 
      "lat": 50.480977760717, 
      "lon": 4.119769749554, 
      "municipality": "La Louvi\u00e8re", 
      "pcode": "7110", 
      "source": "7717479", 
      "street": "Rue des Sports"
    }, 
    {
      "hnrlbls": [
        "50"
      ], 
      "housenumber": "50", 
      "lat": 50.482050977405, 
      "lon": 4.12012931403, 
      "municipality": "La Louvi\u00e8re", 
      "pcode": "7110", 
      "source": "7717479", 
      "street": "Rue des Sports"
    }, 
    {
      "hnrlbls": [
        "51"
      ], 
      "housenumber": "51", 
      "lat": 50.482102297789, 
      "lon": 4.119468653466, 
      "municipality": "La Louvi\u00e8re", 
      "pcode": "7110", 
      "source": "7717479", 
      "street": "Rue des Sports"
    }, 
    {
      "hnrlbls": [
        "52"
      ], 
      "housenumber": "52", 
      "lat": 50.482213984852, 
      "lon": 4.120126360106, 
      "municipality": "La Louvi\u00e8re", 
      "pcode": "7110", 
      "source": "7717479", 
      "street": "Rue des Sports"
    }, 
    {
      "hnrlbls": [
        "53"
      ], 
      "housenumber": "53", 
      "lat": 50.482338079959, 
      "lon": 4.119448929886, 
      "municipality": "La Louvi\u00e8re", 
      "pcode": "7110", 
      "source": "7717479", 
      "street": "Rue des Sports"
    }, 
    {
      "hnrlbls": [
        "54"
      ], 
      "housenumber": "54", 
      "lat": 50.482256886055, 
      "lon": 4.120138802658, 
      "municipality": "La Louvi\u00e8re", 
      "pcode": "7110", 
      "source": "7717479", 
      "street": "Rue des Sports"
    }, 
    {
      "hnrlbls": [
        "56"
      ], 
      "housenumber": "56", 
      "lat": 50.482299499389, 
      "lon": 4.120151162198, 
      "municipality": "La Louvi\u00e8re", 
      "pcode": "7110", 
      "source": "7717479", 
      "street": "Rue des Sports"
    }, 
    {
      "hnrlbls": [
        "58"
      ], 
      "housenumber": "58", 
      "lat": 50.482339521897, 
      "lon": 4.120162760356, 
      "municipality": "La Louvi\u00e8re", 
      "pcode": "7110", 
      "source": "7717479", 
      "street": "Rue des Sports"
    }, 
    {
      "hnrlbls": [
        "6"
      ], 
      "housenumber": "6", 
      "lat": 50.481170209312, 
      "lon": 4.120150378868, 
      "municipality": "La Louvi\u00e8re", 
      "pcode": "7110", 
      "source": "7717479", 
      "street": "Rue des Sports"
    }, 
    {
      "hnrlbls": [
        "60"
      ], 
      "housenumber": "60", 
      "lat": 50.48238123564, 
      "lon": 4.120174856932, 
      "municipality": "La Louvi\u00e8re", 
      "pcode": "7110", 
      "source": "7717479", 
      "street": "Rue des Sports"
    }, 
    {
      "hnrlbls": [
        "62"
      ], 
      "housenumber": "62", 
      "lat": 50.482421141212, 
      "lon": 4.120186427561, 
      "municipality": "La Louvi\u00e8re", 
      "pcode": "7110", 
      "source": "7717479", 
      "street": "Rue des Sports"
    }, 
    {
      "hnrlbls": [
        "64"
      ], 
      "housenumber": "64", 
      "lat": 50.482463493646, 
      "lon": 4.12019870401, 
      "municipality": "La Louvi\u00e8re", 
      "pcode": "7110", 
      "source": "7717479", 
      "street": "Rue des Sports"
    }, 
    {
      "hnrlbls": [
        "66"
      ], 
      "housenumber": "66", 
      "lat": 50.482506511801, 
      "lon": 4.120211188352, 
      "municipality": "La Louvi\u00e8re", 
      "pcode": "7110", 
      "source": "7717479", 
      "street": "Rue des Sports"
    }, 
    {
      "hnrlbls": [
        "68"
      ], 
      "housenumber": "68", 
      "lat": 50.48254927805, 
      "lon": 4.120223589493, 
      "municipality": "La Louvi\u00e8re", 
      "pcode": "7110", 
      "source": "7717479", 
      "street": "Rue des Sports"
    }, 
    {
      "hnrlbls": [
        "6A"
      ], 
      "housenumber": "6A", 
      "lat": 50.481082287159, 
      "lon": 4.120514920211, 
      "municipality": "La Louvi\u00e8re", 
      "pcode": "7110", 
      "source": "7717479", 
      "street": "Rue des Sports"
    }, 
    {
      "hnrlbls": [
        "6B"
      ], 
      "housenumber": "6B", 
      "lat": 50.48108578321, 
      "lon": 4.120734224285, 
      "municipality": "La Louvi\u00e8re", 
      "pcode": "7110", 
      "source": "7717479", 
      "street": "Rue des Sports"
    }, 
    {
      "hnrlbls": [
        "6C"
      ], 
      "housenumber": "6C", 
      "lat": 50.481236847178, 
      "lon": 4.120873897647, 
      "municipality": "La Louvi\u00e8re", 
      "pcode": "7110", 
      "source": "7717479", 
      "street": "Rue des Sports"
    }, 
    {
      "hnrlbls": [
        "6D"
      ], 
      "housenumber": "6D", 
      "lat": 50.481375998631, 
      "lon": 4.120869536415, 
      "municipality": "La Louvi\u00e8re", 
      "pcode": "7110", 
      "source": "7717479", 
      "street": "Rue des Sports"
    }, 
    {
      "hnrlbls": [
        "6E"
      ], 
      "housenumber": "6E", 
      "lat": 50.481477281006, 
      "lon": 4.120673876248, 
      "municipality": "La Louvi\u00e8re", 
      "pcode": "7110", 
      "source": "7717479", 
      "street": "Rue des Sports"
    }, 
    {
      "hnrlbls": [
        "6F"
      ], 
      "housenumber": "6F", 
      "lat": 50.481458968442, 
      "lon": 4.120458607078, 
      "municipality": "La Louvi\u00e8re", 
      "pcode": "7110", 
      "source": "7717479", 
      "street": "Rue des Sports"
    }, 
    {
      "hnrlbls": [
        "7"
      ], 
      "housenumber": "7", 
      "lat": 50.48103703645, 
      "lon": 4.119758392482, 
      "municipality": "La Louvi\u00e8re", 
      "pcode": "7110", 
      "source": "7717479", 
      "street": "Rue des Sports"
    }, 
    {
      "hnrlbls": [
        "70"
      ], 
      "housenumber": "70", 
      "lat": 50.482589984974, 
      "lon": 4.120235733714, 
      "municipality": "La Louvi\u00e8re", 
      "pcode": "7110", 
      "source": "7717479", 
      "street": "Rue des Sports"
    }, 
    {
      "hnrlbls": [
        "72"
      ], 
      "housenumber": "72", 
      "lat": 50.482634290642, 
      "lon": 4.120249113166, 
      "municipality": "La Louvi\u00e8re", 
      "pcode": "7110", 
      "source": "7717479", 
      "street": "Rue des Sports"
    }, 
    {
      "hnrlbls": [
        "74"
      ], 
      "housenumber": "74", 
      "lat": 50.482714404958, 
      "lon": 4.120490737571, 
      "municipality": "La Louvi\u00e8re", 
      "pcode": "7110", 
      "source": "7717479", 
      "street": "Rue des Sports"
    }, 
    {
      "hnrlbls": [
        "76"
      ], 
      "housenumber": "76", 
      "lat": 50.482702390822, 
      "lon": 4.120565352205, 
      "municipality": "La Louvi\u00e8re", 
      "pcode": "7110", 
      "source": "7717479", 
      "street": "Rue des Sports"
    }, 
    {
      "hnrlbls": [
        "77"
      ], 
      "housenumber": "77", 
      "lat": 50.482865430626, 
      "lon": 4.12059114532, 
      "municipality": "La Louvi\u00e8re", 
      "pcode": "7110", 
      "source": "7717479", 
      "street": "Rue des Sports"
    }, 
    {
      "hnrlbls": [
        "78"
      ], 
      "housenumber": "78", 
      "lat": 50.48263874538, 
      "lon": 4.12094458682, 
      "municipality": "La Louvi\u00e8re", 
      "pcode": "7110", 
      "source": "7717479", 
      "street": "Rue des Sports"
    }, 
    {
      "hnrlbls": [
        "79"
      ], 
      "housenumber": "79", 
      "lat": 50.483107461043, 
      "lon": 4.119352670399, 
      "municipality": "La Louvi\u00e8re", 
      "pcode": "7110", 
      "source": "7717479", 
      "street": "Rue des Sports"
    }, 
    {
      "hnrlbls": [
        "8"
      ], 
      "housenumber": "8", 
      "lat": 50.481430962141, 
      "lon": 4.120094782225, 
      "municipality": "La Louvi\u00e8re", 
      "pcode": "7110", 
      "source": "7717479", 
      "street": "Rue des Sports"
    }, 
    {
      "hnrlbls": [
        "80"
      ], 
      "housenumber": "80", 
      "lat": 50.482626392543, 
      "lon": 4.121016483559, 
      "municipality": "La Louvi\u00e8re", 
      "pcode": "7110", 
      "source": "7717479", 
      "street": "Rue des Sports"
    }, 
    {
      "hnrlbls": [
        "81"
      ], 
      "housenumber": "81", 
      "lat": 50.48321505143, 
      "lon": 4.119341734979, 
      "municipality": "La Louvi\u00e8re", 
      "pcode": "7110", 
      "source": "7717479", 
      "street": "Rue des Sports"
    }, 
    {
      "hnrlbls": [
        "83"
      ], 
      "housenumber": "83", 
      "lat": 50.483419707638, 
      "lon": 4.11932130012, 
      "municipality": "La Louvi\u00e8re", 
      "pcode": "7110", 
      "source": "7717479", 
      "street": "Rue des Sports"
    }, 
    {
      "hnrlbls": [
        "85"
      ], 
      "housenumber": "85", 
      "lat": 50.483529156034, 
      "lon": 4.119308973925, 
      "municipality": "La Louvi\u00e8re", 
      "pcode": "7110", 
      "source": "7717479", 
      "street": "Rue des Sports"
    }, 
    {
      "hnrlbls": [
        "87"
      ], 
      "housenumber": "87", 
      "lat": 50.483735279253, 
      "lon": 4.119289291979, 
      "municipality": "La Louvi\u00e8re", 
      "pcode": "7110", 
      "source": "7717479", 
      "street": "Rue des Sports"
    }, 
    {
      "hnrlbls": [
        "88"
      ], 
      "housenumber": "88", 
      "lat": 50.482997638834, 
      "lon": 4.119895704893, 
      "municipality": "La Louvi\u00e8re", 
      "pcode": "7110", 
      "source": "7717479", 
      "street": "Rue des Sports"
    }, 
    {
      "hnrlbls": [
        "89"
      ], 
      "housenumber": "89", 
      "lat": 50.483843532848, 
      "lon": 4.119277394622, 
      "municipality": "La Louvi\u00e8re", 
      "pcode": "7110", 
      "source": "7717479", 
      "street": "Rue des Sports"
    }, 
    {
      "hnrlbls": [
        "9"
      ], 
      "housenumber": "9", 
      "lat": 50.481096698128, 
      "lon": 4.11974252461, 
      "municipality": "La Louvi\u00e8re", 
      "pcode": "7110", 
      "source": "7717479", 
      "street": "Rue des Sports"
    }, 
    {
      "hnrlbls": [
        "94"
      ], 
      "housenumber": "94", 
      "lat": 50.483443124055, 
      "lon": 4.119715444425, 
      "municipality": "La Louvi\u00e8re", 
      "pcode": "7110", 
      "source": "7717479", 
      "street": "Rue des Sports"
    }, 
    {
      "hnrlbls": [
        "96"
      ], 
      "housenumber": "96", 
      "lat": 50.483594152935, 
      "lon": 4.11974878712, 
      "municipality": "La Louvi\u00e8re", 
      "pcode": "7110", 
      "source": "7717479", 
      "street": "Rue des Sports"
    }, 
    {
      "hnrlbls": [
        "98"
      ], 
      "housenumber": "98", 
      "lat": 50.483661414479, 
      "lon": 4.119741954297, 
      "municipality": "La Louvi\u00e8re", 
      "pcode": "7110", 
      "source": "7717479", 
      "street": "Rue des Sports"
    }
  ]
}