{
  "addresses": [
    {
      "hnrlbls": [
        "1"
      ], 
      "housenumber": "1", 
      "lat": 50.200058239088, 
      "lon": 4.839429213419, 
      "municipality": "Hasti\u00e8re", 
      "pcode": "5542", 
      "source": "7751084", 
      "street": "Rue du Domaine du Bonsoy"
    }, 
    {
      "hnrlbls": [
        "10"
      ], 
      "housenumber": "10", 
      "lat": 50.19984985442, 
      "lon": 4.839254454494, 
      "municipality": "Hasti\u00e8re", 
      "pcode": "5542", 
      "source": "7751084", 
      "street": "Rue du Domaine du Bonsoy"
    }, 
    {
      "hnrlbls": [
        "11"
      ], 
      "housenumber": "11", 
      "lat": 50.199861960254, 
      "lon": 4.839348521237, 
      "municipality": "Hasti\u00e8re", 
      "pcode": "5542", 
      "source": "7751084", 
      "street": "Rue du Domaine du Bonsoy"
    }, 
    {
      "hnrlbls": [
        "12"
      ], 
      "housenumber": "12", 
      "lat": 50.19987337846, 
      "lon": 4.839435909741, 
      "municipality": "Hasti\u00e8re", 
      "pcode": "5542", 
      "source": "7751084", 
      "street": "Rue du Domaine du Bonsoy"
    }, 
    {
      "hnrlbls": [
        "13"
      ], 
      "housenumber": "13", 
      "lat": 50.19998233147, 
      "lon": 4.839230747832, 
      "municipality": "Hasti\u00e8re", 
      "pcode": "5542", 
      "source": "7751084", 
      "street": "Rue du Domaine du Bonsoy"
    }, 
    {
      "hnrlbls": [
        "2"
      ], 
      "housenumber": "2", 
      "lat": 50.200048070246, 
      "lon": 4.839385381744, 
      "municipality": "Hasti\u00e8re", 
      "pcode": "5542", 
      "source": "7751084", 
      "street": "Rue du Domaine du Bonsoy"
    }, 
    {
      "hnrlbls": [
        "3"
      ], 
      "housenumber": "3", 
      "lat": 50.200037555644, 
      "lon": 4.839338582798, 
      "municipality": "Hasti\u00e8re", 
      "pcode": "5542", 
      "source": "7751084", 
      "street": "Rue du Domaine du Bonsoy"
    }, 
    {
      "hnrlbls": [
        "4"
      ], 
      "housenumber": "4", 
      "lat": 50.200025637796, 
      "lon": 4.839286210642, 
      "municipality": "Hasti\u00e8re", 
      "pcode": "5542", 
      "source": "7751084", 
      "street": "Rue du Domaine du Bonsoy"
    }, 
    {
      "hnrlbls": [
        "5"
      ], 
      "housenumber": "5", 
      "lat": 50.200013694123, 
      "lon": 4.839239952288, 
      "municipality": "Hasti\u00e8re", 
      "pcode": "5542", 
      "source": "7751084", 
      "street": "Rue du Domaine du Bonsoy"
    }, 
    {
      "hnrlbls": [
        "6"
      ], 
      "housenumber": "6", 
      "lat": 50.200001748167, 
      "lon": 4.83919425001, 
      "municipality": "Hasti\u00e8re", 
      "pcode": "5542", 
      "source": "7751084", 
      "street": "Rue du Domaine du Bonsoy"
    }, 
    {
      "hnrlbls": [
        "7"
      ], 
      "housenumber": "7", 
      "lat": 50.199947069293, 
      "lon": 4.839127557612, 
      "municipality": "Hasti\u00e8re", 
      "pcode": "5542", 
      "source": "7751084", 
      "street": "Rue du Domaine du Bonsoy"
    }, 
    {
      "hnrlbls": [
        "8"
      ], 
      "housenumber": "8", 
      "lat": 50.199919112649, 
      "lon": 4.839070579909, 
      "municipality": "Hasti\u00e8re", 
      "pcode": "5542", 
      "source": "7751084", 
      "street": "Rue du Domaine du Bonsoy"
    }
  ]
}