{
  "addresses": [
    {
      "hnrlbls": [
        "10"
      ], 
      "housenumber": "10", 
      "lat": 50.648555019271, 
      "lon": 5.581578312924, 
      "municipality": "Li\u00e8ge", 
      "pcode": "4000", 
      "source": "7729888", 
      "street": "Impasse Hubart"
    }, 
    {
      "hnrlbls": [
        "11"
      ], 
      "housenumber": "11", 
      "lat": 50.64873510171, 
      "lon": 5.58114835458, 
      "municipality": "Li\u00e8ge", 
      "pcode": "4000", 
      "source": "7729888", 
      "street": "Impasse Hubart"
    }, 
    {
      "hnrlbls": [
        "12"
      ], 
      "housenumber": "12", 
      "lat": 50.648593170043, 
      "lon": 5.581485605364, 
      "municipality": "Li\u00e8ge", 
      "pcode": "4000", 
      "source": "7729888", 
      "street": "Impasse Hubart"
    }, 
    {
      "hnrlbls": [
        "13"
      ], 
      "housenumber": "13", 
      "lat": 50.648808806331, 
      "lon": 5.581115064143, 
      "municipality": "Li\u00e8ge", 
      "pcode": "4000", 
      "source": "7729888", 
      "street": "Impasse Hubart"
    }, 
    {
      "hnrlbls": [
        "14"
      ], 
      "housenumber": "14", 
      "lat": 50.648651069648, 
      "lon": 5.581426228045, 
      "municipality": "Li\u00e8ge", 
      "pcode": "4000", 
      "source": "7729888", 
      "street": "Impasse Hubart"
    }, 
    {
      "hnrlbls": [
        "15"
      ], 
      "housenumber": "15", 
      "lat": 50.648880932307, 
      "lon": 5.581044186772, 
      "municipality": "Li\u00e8ge", 
      "pcode": "4000", 
      "source": "7729888", 
      "street": "Impasse Hubart"
    }, 
    {
      "hnrlbls": [
        "16"
      ], 
      "housenumber": "16", 
      "lat": 50.648695720301, 
      "lon": 5.581408864326, 
      "municipality": "Li\u00e8ge", 
      "pcode": "4000", 
      "source": "7729888", 
      "street": "Impasse Hubart"
    }, 
    {
      "hnrlbls": [
        "17"
      ], 
      "housenumber": "17", 
      "lat": 50.648929110789, 
      "lon": 5.580998799494, 
      "municipality": "Li\u00e8ge", 
      "pcode": "4000", 
      "source": "7729888", 
      "street": "Impasse Hubart"
    }, 
    {
      "hnrlbls": [
        "18"
      ], 
      "housenumber": "18", 
      "lat": 50.648811643323, 
      "lon": 5.581365586528, 
      "municipality": "Li\u00e8ge", 
      "pcode": "4000", 
      "source": "7729888", 
      "street": "Impasse Hubart"
    }, 
    {
      "hnrlbls": [
        "19"
      ], 
      "housenumber": "19", 
      "lat": 50.648794475024, 
      "lon": 5.580782592353, 
      "municipality": "Li\u00e8ge", 
      "pcode": "4000", 
      "source": "7729888", 
      "street": "Impasse Hubart"
    }, 
    {
      "hnrlbls": [
        "20"
      ], 
      "housenumber": "20", 
      "lat": 50.648853581664, 
      "lon": 5.58124494677, 
      "municipality": "Li\u00e8ge", 
      "pcode": "4000", 
      "source": "7729888", 
      "street": "Impasse Hubart"
    }, 
    {
      "hnrlbls": [
        "21"
      ], 
      "housenumber": "21", 
      "lat": 50.648873242737, 
      "lon": 5.580669530686, 
      "municipality": "Li\u00e8ge", 
      "pcode": "4000", 
      "source": "7729888", 
      "street": "Impasse Hubart"
    }, 
    {
      "hnrlbls": [
        "22"
      ], 
      "housenumber": "22", 
      "lat": 50.64891170742, 
      "lon": 5.581188021163, 
      "municipality": "Li\u00e8ge", 
      "pcode": "4000", 
      "source": "7729888", 
      "street": "Impasse Hubart"
    }, 
    {
      "hnrlbls": [
        "23"
      ], 
      "housenumber": "23", 
      "lat": 50.648981241458, 
      "lon": 5.580875875477, 
      "municipality": "Li\u00e8ge", 
      "pcode": "4000", 
      "source": "7729888", 
      "street": "Impasse Hubart"
    }, 
    {
      "hnrlbls": [
        "26"
      ], 
      "housenumber": "26", 
      "lat": 50.648975057409, 
      "lon": 5.58059950001, 
      "municipality": "Li\u00e8ge", 
      "pcode": "4000", 
      "source": "7729888", 
      "street": "Impasse Hubart"
    }, 
    {
      "hnrlbls": [
        "4"
      ], 
      "housenumber": "4", 
      "lat": 50.648357524399, 
      "lon": 5.581730984976, 
      "municipality": "Li\u00e8ge", 
      "pcode": "4000", 
      "source": "7729888", 
      "street": "Impasse Hubart"
    }, 
    {
      "hnrlbls": [
        "6"
      ], 
      "housenumber": "6", 
      "lat": 50.648448347181, 
      "lon": 5.581645034144, 
      "municipality": "Li\u00e8ge", 
      "pcode": "4000", 
      "source": "7729888", 
      "street": "Impasse Hubart"
    }, 
    {
      "hnrlbls": [
        "8"
      ], 
      "housenumber": "8", 
      "lat": 50.648515070122, 
      "lon": 5.581638151422, 
      "municipality": "Li\u00e8ge", 
      "pcode": "4000", 
      "source": "7729888", 
      "street": "Impasse Hubart"
    }
  ]
}