{
  "addresses": [
    {
      "hnrlbls": [
        "1"
      ], 
      "housenumber": "1", 
      "lat": 50.411068762931, 
      "lon": 3.85494271441, 
      "municipality": "Colfontaine", 
      "pcode": "7340", 
      "source": "7715026", 
      "street": "Rue de Maubeuge"
    }, 
    {
      "hnrlbls": [
        "10"
      ], 
      "housenumber": "10", 
      "lat": 50.411766980412, 
      "lon": 3.854495477189, 
      "municipality": "Colfontaine", 
      "pcode": "7340", 
      "source": "7715026", 
      "street": "Rue de Maubeuge"
    }, 
    {
      "hnrlbls": [
        "12"
      ], 
      "housenumber": "12", 
      "lat": 50.411823096056, 
      "lon": 3.854492674935, 
      "municipality": "Colfontaine", 
      "pcode": "7340", 
      "source": "7715026", 
      "street": "Rue de Maubeuge"
    }, 
    {
      "hnrlbls": [
        "16"
      ], 
      "housenumber": "16", 
      "lat": 50.411926046487, 
      "lon": 3.85448648146, 
      "municipality": "Colfontaine", 
      "pcode": "7340", 
      "source": "7715026", 
      "street": "Rue de Maubeuge"
    }, 
    {
      "hnrlbls": [
        "17"
      ], 
      "housenumber": "17", 
      "lat": 50.411861144868, 
      "lon": 3.854826555231, 
      "municipality": "Colfontaine", 
      "pcode": "7340", 
      "source": "7715026", 
      "street": "Rue de Maubeuge"
    }, 
    {
      "hnrlbls": [
        "17A"
      ], 
      "housenumber": "17A", 
      "lat": 50.411917634148, 
      "lon": 3.854812676585, 
      "municipality": "Colfontaine", 
      "pcode": "7340", 
      "source": "7715026", 
      "street": "Rue de Maubeuge"
    }, 
    {
      "hnrlbls": [
        "18"
      ], 
      "housenumber": "18", 
      "lat": 50.412012248671, 
      "lon": 3.854474447471, 
      "municipality": "Colfontaine", 
      "pcode": "7340", 
      "source": "7715026", 
      "street": "Rue de Maubeuge"
    }, 
    {
      "hnrlbls": [
        "19"
      ], 
      "housenumber": "19", 
      "lat": 50.412026789907, 
      "lon": 3.854857784714, 
      "municipality": "Colfontaine", 
      "pcode": "7340", 
      "source": "7715026", 
      "street": "Rue de Maubeuge"
    }, 
    {
      "hnrlbls": [
        "2"
      ], 
      "housenumber": "2", 
      "lat": 50.411465933588, 
      "lon": 3.854514212119, 
      "municipality": "Colfontaine", 
      "pcode": "7340", 
      "source": "7715026", 
      "street": "Rue de Maubeuge"
    }, 
    {
      "hnrlbls": [
        "20"
      ], 
      "housenumber": "20", 
      "lat": 50.412054890354, 
      "lon": 3.854458059108, 
      "municipality": "Colfontaine", 
      "pcode": "7340", 
      "source": "7715026", 
      "street": "Rue de Maubeuge"
    }, 
    {
      "hnrlbls": [
        "21"
      ], 
      "housenumber": "21", 
      "lat": 50.412116368793, 
      "lon": 3.854800115242, 
      "municipality": "Colfontaine", 
      "pcode": "7340", 
      "source": "7715026", 
      "street": "Rue de Maubeuge"
    }, 
    {
      "hnrlbls": [
        "22"
      ], 
      "housenumber": "22", 
      "lat": 50.412105176127, 
      "lon": 3.85444215075, 
      "municipality": "Colfontaine", 
      "pcode": "7340", 
      "source": "7715026", 
      "street": "Rue de Maubeuge"
    }, 
    {
      "hnrlbls": [
        "23"
      ], 
      "housenumber": "23", 
      "lat": 50.412432259866, 
      "lon": 3.854885379297, 
      "municipality": "Colfontaine", 
      "pcode": "7340", 
      "source": "7715026", 
      "street": "Rue de Maubeuge"
    }, 
    {
      "hnrlbls": [
        "24"
      ], 
      "housenumber": "24", 
      "lat": 50.4121885661, 
      "lon": 3.854312581232, 
      "municipality": "Colfontaine", 
      "pcode": "7340", 
      "source": "7715026", 
      "street": "Rue de Maubeuge"
    }, 
    {
      "hnrlbls": [
        "24A"
      ], 
      "housenumber": "24A", 
      "lat": 50.412290572387, 
      "lon": 3.854320593831, 
      "municipality": "Colfontaine", 
      "pcode": "7340", 
      "source": "7715026", 
      "street": "Rue de Maubeuge"
    }, 
    {
      "hnrlbls": [
        "25"
      ], 
      "housenumber": "25", 
      "lat": 50.412483789153, 
      "lon": 3.854859918546, 
      "municipality": "Colfontaine", 
      "pcode": "7340", 
      "source": "7715026", 
      "street": "Rue de Maubeuge"
    }, 
    {
      "hnrlbls": [
        "26"
      ], 
      "housenumber": "26", 
      "lat": 50.412353169344, 
      "lon": 3.854250496223, 
      "municipality": "Colfontaine", 
      "pcode": "7340", 
      "source": "7715026", 
      "street": "Rue de Maubeuge"
    }, 
    {
      "hnrlbls": [
        "26A"
      ], 
      "housenumber": "26A", 
      "lat": 50.412321511719, 
      "lon": 3.854280568276, 
      "municipality": "Colfontaine", 
      "pcode": "7340", 
      "source": "7715026", 
      "street": "Rue de Maubeuge"
    }, 
    {
      "hnrlbls": [
        "26B"
      ], 
      "housenumber": "26B", 
      "lat": 50.412382234631, 
      "lon": 3.85420753623, 
      "municipality": "Colfontaine", 
      "pcode": "7340", 
      "source": "7715026", 
      "street": "Rue de Maubeuge"
    }, 
    {
      "hnrlbls": [
        "27"
      ], 
      "housenumber": "27", 
      "lat": 50.412569966018, 
      "lon": 3.854823826104, 
      "municipality": "Colfontaine", 
      "pcode": "7340", 
      "source": "7715026", 
      "street": "Rue de Maubeuge"
    }, 
    {
      "hnrlbls": [
        "28"
      ], 
      "housenumber": "28", 
      "lat": 50.412424973595, 
      "lon": 3.854115578073, 
      "municipality": "Colfontaine", 
      "pcode": "7340", 
      "source": "7715026", 
      "street": "Rue de Maubeuge"
    }, 
    {
      "hnrlbls": [
        "29B"
      ], 
      "housenumber": "29B", 
      "lat": 50.412716459307, 
      "lon": 3.854844457609, 
      "municipality": "Colfontaine", 
      "pcode": "7340", 
      "source": "7715026", 
      "street": "Rue de Maubeuge"
    }, 
    {
      "hnrlbls": [
        "31"
      ], 
      "housenumber": "31", 
      "lat": 50.412938508468, 
      "lon": 3.854799789836, 
      "municipality": "Colfontaine", 
      "pcode": "7340", 
      "source": "7715026", 
      "street": "Rue de Maubeuge"
    }, 
    {
      "hnrlbls": [
        "31A"
      ], 
      "housenumber": "31A", 
      "lat": 50.412848089791, 
      "lon": 3.854807774763, 
      "municipality": "Colfontaine", 
      "pcode": "7340", 
      "source": "7715026", 
      "street": "Rue de Maubeuge"
    }, 
    {
      "hnrlbls": [
        "31B"
      ], 
      "housenumber": "31B", 
      "lat": 50.412874447744, 
      "lon": 3.854768572462, 
      "municipality": "Colfontaine", 
      "pcode": "7340", 
      "source": "7715026", 
      "street": "Rue de Maubeuge"
    }, 
    {
      "hnrlbls": [
        "32"
      ], 
      "housenumber": "32", 
      "lat": 50.412655170436, 
      "lon": 3.854396773274, 
      "municipality": "Colfontaine", 
      "pcode": "7340", 
      "source": "7715026", 
      "street": "Rue de Maubeuge"
    }, 
    {
      "hnrlbls": [
        "34"
      ], 
      "housenumber": "34", 
      "lat": 50.412716090199, 
      "lon": 3.854331645955, 
      "municipality": "Colfontaine", 
      "pcode": "7340", 
      "source": "7715026", 
      "street": "Rue de Maubeuge"
    }, 
    {
      "hnrlbls": [
        "35"
      ], 
      "housenumber": "35", 
      "lat": 50.41309705964, 
      "lon": 3.854745467255, 
      "municipality": "Colfontaine", 
      "pcode": "7340", 
      "source": "7715026", 
      "street": "Rue de Maubeuge"
    }, 
    {
      "hnrlbls": [
        "36"
      ], 
      "housenumber": "36", 
      "lat": 50.412761943902, 
      "lon": 3.854283269919, 
      "municipality": "Colfontaine", 
      "pcode": "7340", 
      "source": "7715026", 
      "street": "Rue de Maubeuge"
    }, 
    {
      "hnrlbls": [
        "37"
      ], 
      "housenumber": "37", 
      "lat": 50.413248587959, 
      "lon": 3.854766170903, 
      "municipality": "Colfontaine", 
      "pcode": "7340", 
      "source": "7715026", 
      "street": "Rue de Maubeuge"
    }, 
    {
      "hnrlbls": [
        "38"
      ], 
      "housenumber": "38", 
      "lat": 50.412974706107, 
      "lon": 3.85413096709, 
      "municipality": "Colfontaine", 
      "pcode": "7340", 
      "source": "7715026", 
      "street": "Rue de Maubeuge"
    }, 
    {
      "hnrlbls": [
        "38A"
      ], 
      "housenumber": "38A", 
      "lat": 50.413067039856, 
      "lon": 3.854320220006, 
      "municipality": "Colfontaine", 
      "pcode": "7340", 
      "source": "7715026", 
      "street": "Rue de Maubeuge"
    }, 
    {
      "hnrlbls": [
        "38D"
      ], 
      "housenumber": "38D", 
      "lat": 50.413381442792, 
      "lon": 3.853877860134, 
      "municipality": "Colfontaine", 
      "pcode": "7340", 
      "source": "7715026", 
      "street": "Rue de Maubeuge"
    }, 
    {
      "hnrlbls": [
        "38F"
      ], 
      "housenumber": "38F", 
      "lat": 50.413706793796, 
      "lon": 3.853573389077, 
      "municipality": "Colfontaine", 
      "pcode": "7340", 
      "source": "7715026", 
      "street": "Rue de Maubeuge"
    }, 
    {
      "hnrlbls": [
        "39"
      ], 
      "housenumber": "39", 
      "lat": 50.413658829792, 
      "lon": 3.854473844866, 
      "municipality": "Colfontaine", 
      "pcode": "7340", 
      "source": "7715026", 
      "street": "Rue de Maubeuge"
    }, 
    {
      "hnrlbls": [
        "39B"
      ], 
      "housenumber": "39B", 
      "lat": 50.413560238521, 
      "lon": 3.854864342652, 
      "municipality": "Colfontaine", 
      "pcode": "7340", 
      "source": "7715026", 
      "street": "Rue de Maubeuge"
    }, 
    {
      "hnrlbls": [
        "39C"
      ], 
      "housenumber": "39C", 
      "lat": 50.413526951673, 
      "lon": 3.854539910168, 
      "municipality": "Colfontaine", 
      "pcode": "7340", 
      "source": "7715026", 
      "street": "Rue de Maubeuge"
    }, 
    {
      "hnrlbls": [
        "39D"
      ], 
      "housenumber": "39D", 
      "lat": 50.413598246475, 
      "lon": 3.854517470618, 
      "municipality": "Colfontaine", 
      "pcode": "7340", 
      "source": "7715026", 
      "street": "Rue de Maubeuge"
    }, 
    {
      "hnrlbls": [
        "4"
      ], 
      "housenumber": "4", 
      "lat": 50.411528830934, 
      "lon": 3.854510013975, 
      "municipality": "Colfontaine", 
      "pcode": "7340", 
      "source": "7715026", 
      "street": "Rue de Maubeuge"
    }, 
    {
      "hnrlbls": [
        "40"
      ], 
      "housenumber": "40", 
      "lat": 50.413862666907, 
      "lon": 3.853555996506, 
      "municipality": "Colfontaine", 
      "pcode": "7340", 
      "source": "7715026", 
      "street": "Rue de Maubeuge"
    }, 
    {
      "hnrlbls": [
        "41"
      ], 
      "housenumber": "41", 
      "lat": 50.413759583111, 
      "lon": 3.854066325342, 
      "municipality": "Colfontaine", 
      "pcode": "7340", 
      "source": "7715026", 
      "street": "Rue de Maubeuge"
    }, 
    {
      "hnrlbls": [
        "43"
      ], 
      "housenumber": "43", 
      "lat": 50.413846738854, 
      "lon": 3.854009719708, 
      "municipality": "Colfontaine", 
      "pcode": "7340", 
      "source": "7715026", 
      "street": "Rue de Maubeuge"
    }, 
    {
      "hnrlbls": [
        "45"
      ], 
      "housenumber": "45", 
      "lat": 50.413954430363, 
      "lon": 3.853859957955, 
      "municipality": "Colfontaine", 
      "pcode": "7340", 
      "source": "7715026", 
      "street": "Rue de Maubeuge"
    }, 
    {
      "hnrlbls": [
        "47"
      ], 
      "housenumber": "47", 
      "lat": 50.414012115112, 
      "lon": 3.853762755088, 
      "municipality": "Colfontaine", 
      "pcode": "7340", 
      "source": "7715026", 
      "street": "Rue de Maubeuge"
    }, 
    {
      "hnrlbls": [
        "49"
      ], 
      "housenumber": "49", 
      "lat": 50.414063986661, 
      "lon": 3.85370702358, 
      "municipality": "Colfontaine", 
      "pcode": "7340", 
      "source": "7715026", 
      "street": "Rue de Maubeuge"
    }, 
    {
      "hnrlbls": [
        "50"
      ], 
      "housenumber": "50", 
      "lat": 50.41416983247, 
      "lon": 3.853242121583, 
      "municipality": "Colfontaine", 
      "pcode": "7340", 
      "source": "7715026", 
      "street": "Rue de Maubeuge"
    }, 
    {
      "hnrlbls": [
        "51"
      ], 
      "housenumber": "51", 
      "lat": 50.414097978641, 
      "lon": 3.853651893845, 
      "municipality": "Colfontaine", 
      "pcode": "7340", 
      "source": "7715026", 
      "street": "Rue de Maubeuge"
    }, 
    {
      "hnrlbls": [
        "53"
      ], 
      "housenumber": "53", 
      "lat": 50.41413190451, 
      "lon": 3.853612298259, 
      "municipality": "Colfontaine", 
      "pcode": "7340", 
      "source": "7715026", 
      "street": "Rue de Maubeuge"
    }, 
    {
      "hnrlbls": [
        "54"
      ], 
      "housenumber": "54", 
      "lat": 50.414866414736, 
      "lon": 3.852800672946, 
      "municipality": "Colfontaine", 
      "pcode": "7340", 
      "source": "7715026", 
      "street": "Rue de Maubeuge"
    }, 
    {
      "hnrlbls": [
        "55"
      ], 
      "housenumber": "55", 
      "lat": 50.41415866107, 
      "lon": 3.853577930061, 
      "municipality": "Colfontaine", 
      "pcode": "7340", 
      "source": "7715026", 
      "street": "Rue de Maubeuge"
    }, 
    {
      "hnrlbls": [
        "55B"
      ], 
      "housenumber": "55B", 
      "lat": 50.414181291158, 
      "lon": 3.853549698982, 
      "municipality": "Colfontaine", 
      "pcode": "7340", 
      "source": "7715026", 
      "street": "Rue de Maubeuge"
    }, 
    {
      "hnrlbls": [
        "55C"
      ], 
      "housenumber": "55C", 
      "lat": 50.414208373692, 
      "lon": 3.85351788796, 
      "municipality": "Colfontaine", 
      "pcode": "7340", 
      "source": "7715026", 
      "street": "Rue de Maubeuge"
    }, 
    {
      "hnrlbls": [
        "56"
      ], 
      "housenumber": "56", 
      "lat": 50.414985137993, 
      "lon": 3.852872324816, 
      "municipality": "Colfontaine", 
      "pcode": "7340", 
      "source": "7715026", 
      "street": "Rue de Maubeuge"
    }, 
    {
      "hnrlbls": [
        "57"
      ], 
      "housenumber": "57", 
      "lat": 50.414238076908, 
      "lon": 3.85348504949, 
      "municipality": "Colfontaine", 
      "pcode": "7340", 
      "source": "7715026", 
      "street": "Rue de Maubeuge"
    }, 
    {
      "hnrlbls": [
        "58"
      ], 
      "housenumber": "58", 
      "lat": 50.415034245693, 
      "lon": 3.852874647855, 
      "municipality": "Colfontaine", 
      "pcode": "7340", 
      "source": "7715026", 
      "street": "Rue de Maubeuge"
    }, 
    {
      "hnrlbls": [
        "59"
      ], 
      "housenumber": "59", 
      "lat": 50.414268791904, 
      "lon": 3.853449245252, 
      "municipality": "Colfontaine", 
      "pcode": "7340", 
      "source": "7715026", 
      "street": "Rue de Maubeuge"
    }, 
    {
      "hnrlbls": [
        "59B"
      ], 
      "housenumber": "59B", 
      "lat": 50.414302989305, 
      "lon": 3.853414134845, 
      "municipality": "Colfontaine", 
      "pcode": "7340", 
      "source": "7715026", 
      "street": "Rue de Maubeuge"
    }, 
    {
      "hnrlbls": [
        "6"
      ], 
      "housenumber": "6", 
      "lat": 50.411623569941, 
      "lon": 3.854501095563, 
      "municipality": "Colfontaine", 
      "pcode": "7340", 
      "source": "7715026", 
      "street": "Rue de Maubeuge"
    }, 
    {
      "hnrlbls": [
        "60"
      ], 
      "housenumber": "60", 
      "lat": 50.415086187339, 
      "lon": 3.85287740445, 
      "municipality": "Colfontaine", 
      "pcode": "7340", 
      "source": "7715026", 
      "street": "Rue de Maubeuge"
    }, 
    {
      "hnrlbls": [
        "64"
      ], 
      "housenumber": "64", 
      "lat": 50.41520447065, 
      "lon": 3.852799140138, 
      "municipality": "Colfontaine", 
      "pcode": "7340", 
      "source": "7715026", 
      "street": "Rue de Maubeuge"
    }, 
    {
      "hnrlbls": [
        "66"
      ], 
      "housenumber": "66", 
      "lat": 50.41540565333, 
      "lon": 3.852773035135, 
      "municipality": "Colfontaine", 
      "pcode": "7340", 
      "source": "7715026", 
      "street": "Rue de Maubeuge"
    }, 
    {
      "hnrlbls": [
        "68"
      ], 
      "housenumber": "68", 
      "lat": 50.415589375411, 
      "lon": 3.852801460388, 
      "municipality": "Colfontaine", 
      "pcode": "7340", 
      "source": "7715026", 
      "street": "Rue de Maubeuge"
    }, 
    {
      "hnrlbls": [
        "69"
      ], 
      "housenumber": "69", 
      "lat": 50.414510486441, 
      "lon": 3.853285180743, 
      "municipality": "Colfontaine", 
      "pcode": "7340", 
      "source": "7715026", 
      "street": "Rue de Maubeuge"
    }, 
    {
      "hnrlbls": [
        "7"
      ], 
      "housenumber": "7", 
      "lat": 50.411328521491, 
      "lon": 3.854898710071, 
      "municipality": "Colfontaine", 
      "pcode": "7340", 
      "source": "7715026", 
      "street": "Rue de Maubeuge"
    }, 
    {
      "hnrlbls": [
        "70"
      ], 
      "housenumber": "70", 
      "lat": 50.415781286563, 
      "lon": 3.852803231446, 
      "municipality": "Colfontaine", 
      "pcode": "7340", 
      "source": "7715026", 
      "street": "Rue de Maubeuge"
    }, 
    {
      "hnrlbls": [
        "71"
      ], 
      "housenumber": "71", 
      "lat": 50.414713290653, 
      "lon": 3.853241514822, 
      "municipality": "Colfontaine", 
      "pcode": "7340", 
      "source": "7715026", 
      "street": "Rue de Maubeuge"
    }, 
    {
      "hnrlbls": [
        "73"
      ], 
      "housenumber": "73", 
      "lat": 50.41482351851, 
      "lon": 3.853248437332, 
      "municipality": "Colfontaine", 
      "pcode": "7340", 
      "source": "7715026", 
      "street": "Rue de Maubeuge"
    }, 
    {
      "hnrlbls": [
        "75"
      ], 
      "housenumber": "75", 
      "lat": 50.414877629513, 
      "lon": 3.853286290581, 
      "municipality": "Colfontaine", 
      "pcode": "7340", 
      "source": "7715026", 
      "street": "Rue de Maubeuge"
    }, 
    {
      "hnrlbls": [
        "77"
      ], 
      "housenumber": "77", 
      "lat": 50.414922725951, 
      "lon": 3.853267988083, 
      "municipality": "Colfontaine", 
      "pcode": "7340", 
      "source": "7715026", 
      "street": "Rue de Maubeuge"
    }, 
    {
      "hnrlbls": [
        "79"
      ], 
      "housenumber": "79", 
      "lat": 50.414972665497, 
      "lon": 3.853293701675, 
      "municipality": "Colfontaine", 
      "pcode": "7340", 
      "source": "7715026", 
      "street": "Rue de Maubeuge"
    }, 
    {
      "hnrlbls": [
        "7A"
      ], 
      "housenumber": "7A", 
      "lat": 50.411443127451, 
      "lon": 3.854875043895, 
      "municipality": "Colfontaine", 
      "pcode": "7340", 
      "source": "7715026", 
      "street": "Rue de Maubeuge"
    }, 
    {
      "hnrlbls": [
        "8"
      ], 
      "housenumber": "8", 
      "lat": 50.411716398953, 
      "lon": 3.854497375363, 
      "municipality": "Colfontaine", 
      "pcode": "7340", 
      "source": "7715026", 
      "street": "Rue de Maubeuge"
    }, 
    {
      "hnrlbls": [
        "83"
      ], 
      "housenumber": "83", 
      "lat": 50.415094313501, 
      "lon": 3.853254433633, 
      "municipality": "Colfontaine", 
      "pcode": "7340", 
      "source": "7715026", 
      "street": "Rue de Maubeuge"
    }, 
    {
      "hnrlbls": [
        "85"
      ], 
      "housenumber": "85", 
      "lat": 50.415178212209, 
      "lon": 3.853298830311, 
      "municipality": "Colfontaine", 
      "pcode": "7340", 
      "source": "7715026", 
      "street": "Rue de Maubeuge"
    }, 
    {
      "hnrlbls": [
        "87"
      ], 
      "housenumber": "87", 
      "lat": 50.415296099383, 
      "lon": 3.853262993924, 
      "municipality": "Colfontaine", 
      "pcode": "7340", 
      "source": "7715026", 
      "street": "Rue de Maubeuge"
    }, 
    {
      "hnrlbls": [
        "89"
      ], 
      "housenumber": "89", 
      "lat": 50.415386261408, 
      "lon": 3.853304663509, 
      "municipality": "Colfontaine", 
      "pcode": "7340", 
      "source": "7715026", 
      "street": "Rue de Maubeuge"
    }, 
    {
      "hnrlbls": [
        "9"
      ], 
      "housenumber": "9", 
      "lat": 50.411630731916, 
      "lon": 3.854819761804, 
      "municipality": "Colfontaine", 
      "pcode": "7340", 
      "source": "7715026", 
      "street": "Rue de Maubeuge"
    }, 
    {
      "hnrlbls": [
        "91"
      ], 
      "housenumber": "91", 
      "lat": 50.415561674509, 
      "lon": 3.853314467014, 
      "municipality": "Colfontaine", 
      "pcode": "7340", 
      "source": "7715026", 
      "street": "Rue de Maubeuge"
    }, 
    {
      "hnrlbls": [
        "93"
      ], 
      "housenumber": "93", 
      "lat": 50.415699438129, 
      "lon": 3.853322906175, 
      "municipality": "Colfontaine", 
      "pcode": "7340", 
      "source": "7715026", 
      "street": "Rue de Maubeuge"
    }, 
    {
      "hnrlbls": [
        "95"
      ], 
      "housenumber": "95", 
      "lat": 50.41589203668, 
      "lon": 3.853335759624, 
      "municipality": "Colfontaine", 
      "pcode": "7340", 
      "source": "7715026", 
      "street": "Rue de Maubeuge"
    }, 
    {
      "hnrlbls": [
        "97"
      ], 
      "housenumber": "97", 
      "lat": 50.41605417828, 
      "lon": 3.853339150353, 
      "municipality": "Colfontaine", 
      "pcode": "7340", 
      "source": "7715026", 
      "street": "Rue de Maubeuge"
    }
  ]
}