{
  "addresses": [
    {
      "hnrlbls": [
        "13"
      ], 
      "housenumber": "13", 
      "lat": 50.391383304353, 
      "lon": 6.176116763677, 
      "municipality": "Amel", 
      "pcode": "4770", 
      "source": "7734926", 
      "street": "Helleburen"
    }, 
    {
      "hnrlbls": [
        "16"
      ], 
      "housenumber": "16", 
      "lat": 50.391752649364, 
      "lon": 6.17700191684, 
      "municipality": "Amel", 
      "pcode": "4770", 
      "source": "7734926", 
      "street": "Helleburen"
    }, 
    {
      "hnrlbls": [
        "20"
      ], 
      "housenumber": "20", 
      "lat": 50.392161179023, 
      "lon": 6.176829082179, 
      "municipality": "Amel", 
      "pcode": "4770", 
      "source": "7734926", 
      "street": "Helleburen"
    }, 
    {
      "hnrlbls": [
        "22"
      ], 
      "housenumber": "22", 
      "lat": 50.392385531381, 
      "lon": 6.176446033308, 
      "municipality": "Amel", 
      "pcode": "4770", 
      "source": "7734926", 
      "street": "Helleburen"
    }, 
    {
      "hnrlbls": [
        "23"
      ], 
      "housenumber": "23", 
      "lat": 50.392053720511, 
      "lon": 6.175805740317, 
      "municipality": "Amel", 
      "pcode": "4770", 
      "source": "7734926", 
      "street": "Helleburen"
    }, 
    {
      "hnrlbls": [
        "24"
      ], 
      "housenumber": "24", 
      "lat": 50.39239239158, 
      "lon": 6.17611114832, 
      "municipality": "Amel", 
      "pcode": "4770", 
      "source": "7734926", 
      "street": "Helleburen"
    }, 
    {
      "hnrlbls": [
        "25"
      ], 
      "housenumber": "25", 
      "lat": 50.392099207424, 
      "lon": 6.175291040787, 
      "municipality": "Amel", 
      "pcode": "4770", 
      "source": "7734926", 
      "street": "Helleburen"
    }, 
    {
      "hnrlbls": [
        "26"
      ], 
      "housenumber": "26", 
      "lat": 50.392385378002, 
      "lon": 6.175691695018, 
      "municipality": "Amel", 
      "pcode": "4770", 
      "source": "7734926", 
      "street": "Helleburen"
    }, 
    {
      "hnrlbls": [
        "3"
      ], 
      "housenumber": "3", 
      "lat": 50.390898429259, 
      "lon": 6.177733724881, 
      "municipality": "Amel", 
      "pcode": "4770", 
      "source": "7734926", 
      "street": "Helleburen"
    }, 
    {
      "hnrlbls": [
        "30"
      ], 
      "housenumber": "30", 
      "lat": 50.392465478426, 
      "lon": 6.175038182348, 
      "municipality": "Amel", 
      "pcode": "4770", 
      "source": "7734926", 
      "street": "Helleburen"
    }, 
    {
      "hnrlbls": [
        "31"
      ], 
      "housenumber": "31", 
      "lat": 50.391752956093, 
      "lon": 6.174948340665, 
      "municipality": "Amel", 
      "pcode": "4770", 
      "source": "7734926", 
      "street": "Helleburen"
    }, 
    {
      "hnrlbls": [
        "31A"
      ], 
      "housenumber": "31A", 
      "lat": 50.391709442865, 
      "lon": 6.174806474345, 
      "municipality": "Amel", 
      "pcode": "4770", 
      "source": "7734926", 
      "street": "Helleburen"
    }, 
    {
      "hnrlbls": [
        "4"
      ], 
      "housenumber": "4", 
      "lat": 50.391049009651, 
      "lon": 6.178453700925, 
      "municipality": "Amel", 
      "pcode": "4770", 
      "source": "7734926", 
      "street": "Helleburen"
    }, 
    {
      "hnrlbls": [
        "6"
      ], 
      "housenumber": "6", 
      "lat": 50.391094945574, 
      "lon": 6.17821086645, 
      "municipality": "Amel", 
      "pcode": "4770", 
      "source": "7734926", 
      "street": "Helleburen"
    }, 
    {
      "hnrlbls": [
        "8"
      ], 
      "housenumber": "8", 
      "lat": 50.39147246098, 
      "lon": 6.177733316846, 
      "municipality": "Amel", 
      "pcode": "4770", 
      "source": "7734926", 
      "street": "Helleburen"
    }
  ]
}