{
  "addresses": [
    {
      "hnrlbls": [
        "1"
      ], 
      "housenumber": "1", 
      "lat": 50.504841367479, 
      "lon": 5.663626714663, 
      "municipality": "Sprimont", 
      "pcode": "4140", 
      "source": "7733023", 
      "street": "Rue de l'Agneau"
    }, 
    {
      "hnrlbls": [
        "10"
      ], 
      "housenumber": "10", 
      "lat": 50.503899514743, 
      "lon": 5.663904926031, 
      "municipality": "Sprimont", 
      "pcode": "4140", 
      "source": "7733023", 
      "street": "Rue de l'Agneau"
    }, 
    {
      "hnrlbls": [
        "11"
      ], 
      "housenumber": "11", 
      "lat": 50.503778666063, 
      "lon": 5.663589220834, 
      "municipality": "Sprimont", 
      "pcode": "4140", 
      "source": "7733023", 
      "street": "Rue de l'Agneau"
    }, 
    {
      "hnrlbls": [
        "12"
      ], 
      "housenumber": "12", 
      "lat": 50.503313280752, 
      "lon": 5.66382830129, 
      "municipality": "Sprimont", 
      "pcode": "4140", 
      "source": "7733023", 
      "street": "Rue de l'Agneau"
    }, 
    {
      "hnrlbls": [
        "13"
      ], 
      "housenumber": "13", 
      "lat": 50.503723992638, 
      "lon": 5.663603374425, 
      "municipality": "Sprimont", 
      "pcode": "4140", 
      "source": "7733023", 
      "street": "Rue de l'Agneau"
    }, 
    {
      "hnrlbls": [
        "14"
      ], 
      "housenumber": "14", 
      "lat": 50.503241263155, 
      "lon": 5.663859363273, 
      "municipality": "Sprimont", 
      "pcode": "4140", 
      "source": "7733023", 
      "street": "Rue de l'Agneau"
    }, 
    {
      "hnrlbls": [
        "1B"
      ], 
      "housenumber": "1B", 
      "lat": 50.504725455861, 
      "lon": 5.663501587339, 
      "municipality": "Sprimont", 
      "pcode": "4140", 
      "source": "7733023", 
      "street": "Rue de l'Agneau"
    }, 
    {
      "hnrlbls": [
        "2"
      ], 
      "housenumber": "2", 
      "lat": 50.505124207351, 
      "lon": 5.663956236416, 
      "municipality": "Sprimont", 
      "pcode": "4140", 
      "source": "7733023", 
      "street": "Rue de l'Agneau"
    }, 
    {
      "hnrlbls": [
        "2A"
      ], 
      "housenumber": "2A", 
      "lat": 50.505263851965, 
      "lon": 5.664011477768, 
      "municipality": "Sprimont", 
      "pcode": "4140", 
      "source": "7733023", 
      "street": "Rue de l'Agneau"
    }, 
    {
      "hnrlbls": [
        "3"
      ], 
      "housenumber": "3", 
      "lat": 50.504574478574, 
      "lon": 5.663604185303, 
      "municipality": "Sprimont", 
      "pcode": "4140", 
      "source": "7733023", 
      "street": "Rue de l'Agneau"
    }, 
    {
      "hnrlbls": [
        "4"
      ], 
      "housenumber": "4", 
      "lat": 50.504849558085, 
      "lon": 5.663932153272, 
      "municipality": "Sprimont", 
      "pcode": "4140", 
      "source": "7733023", 
      "street": "Rue de l'Agneau"
    }, 
    {
      "hnrlbls": [
        "5"
      ], 
      "housenumber": "5", 
      "lat": 50.504356624209, 
      "lon": 5.663406804839, 
      "municipality": "Sprimont", 
      "pcode": "4140", 
      "source": "7733023", 
      "street": "Rue de l'Agneau"
    }, 
    {
      "hnrlbls": [
        "5A"
      ], 
      "housenumber": "5A", 
      "lat": 50.504208261463, 
      "lon": 5.663478075857, 
      "municipality": "Sprimont", 
      "pcode": "4140", 
      "source": "7733023", 
      "street": "Rue de l'Agneau"
    }, 
    {
      "hnrlbls": [
        "6"
      ], 
      "housenumber": "6", 
      "lat": 50.504399588835, 
      "lon": 5.664073050502, 
      "municipality": "Sprimont", 
      "pcode": "4140", 
      "source": "7733023", 
      "street": "Rue de l'Agneau"
    }, 
    {
      "hnrlbls": [
        "7"
      ], 
      "housenumber": "7", 
      "lat": 50.503994924334, 
      "lon": 5.66353410447, 
      "municipality": "Sprimont", 
      "pcode": "4140", 
      "source": "7733023", 
      "street": "Rue de l'Agneau"
    }, 
    {
      "hnrlbls": [
        "8"
      ], 
      "housenumber": "8", 
      "lat": 50.504056129873, 
      "lon": 5.663892011721, 
      "municipality": "Sprimont", 
      "pcode": "4140", 
      "source": "7733023", 
      "street": "Rue de l'Agneau"
    }, 
    {
      "hnrlbls": [
        "9"
      ], 
      "housenumber": "9", 
      "lat": 50.503908285202, 
      "lon": 5.663602453094, 
      "municipality": "Sprimont", 
      "pcode": "4140", 
      "source": "7733023", 
      "street": "Rue de l'Agneau"
    }
  ]
}